{
  "slug": "brown-noise",
  "meta": {
    "title": "ADHD फ़ोकस के लिए मुफ़्त ब्राउन नॉइज़ जनरेटर | Doubly",
    "description": "मुफ़्त ब्राउन नॉइज़ जनरेटर जो आपके ब्राउज़र में चलता है। ब्राउन, पिंक और व्हाइट। न साइन-अप, न विज्ञापन, स्लीप टाइमर शामिल। ADHD फ़ोकस के लिए बना।",
    "ogTitle": "ADHD फ़ोकस के लिए मुफ़्त ब्राउन नॉइज़ जनरेटर",
    "ogDescription": "स्लीप टाइमर वाला एक मुफ़्त ब्राउन नॉइज़ प्लेयर। ब्राउन, पिंक और व्हाइट। आपके ब्राउज़र में ऑफ़लाइन चलता है।",
    "twitterTitle": "मुफ़्त ब्राउन नॉइज़ जनरेटर",
    "twitterDescription": "ब्राउन, पिंक और व्हाइट। मुफ़्त, न साइन-अप, आपके ब्राउज़र में चलता है।"
  },
  "h1": "मुफ़्त ब्राउन नॉइज़ जनरेटर",
  "breadcrumbLabel": "ब्राउन नॉइज़ जनरेटर",
  "breadcrumbHome": "होम",
  "breadcrumbTools": "टूल",
  "answerCapsule": "**ब्राउन नॉइज़ एक गहरी, कम फ़्रीक्वेंसी वाली आवाज़ है जो ध्यान भटकाने वाली चीज़ों को ढक देती है और भागते हुए ADHD दिमाग़ को टिकने के लिए कुछ ठहरा हुआ दे देती है।** यह मुफ़्त एंबिएंट साउंड जनरेटर ब्राउन, पिंक और व्हाइट, तीनों को सीधे आपके ब्राउज़र में चलाता है। न साइन-अप, न विज्ञापन, न कोई ऑडियो फ़ाइल डाउनलोड करने की ज़रूरत। एक आवाज़ चुनें, वॉल्यूम सेट करें, चाहें तो स्लीप टाइमर लगाएँ, और वापस काम पर लग जाएँ।",
  "intro": "ऊपर दिया जनरेटर Web Audio API पर चलता है, यानी आवाज़ आपके ही डिवाइस पर उसी वक़्त बनती है। इसका मतलब है न स्ट्रीमिंग, न बफ़रिंग, और वाई-फ़ाई चला जाए तब भी यह चलता रहता है। पहले ब्राउन आज़माएँ। अगर वह ज़्यादा भारी लगे, तो पिंक पर चले जाएँ। ज़्यादातर ADHD वयस्क आख़िर में ब्राउन पर ही टिकते हैं।",
  "sections": [
    {
      "kind": "steps",
      "heading": "ब्राउन नॉइज़ जनरेटर का इस्तेमाल कैसे करें",
      "steps": [
        {
          "name": "एक आवाज़ चुनें",
          "text": "ब्राउन वही गहरी आवाज़ है जिसे ज़्यादातर लोग खोजते हैं। अगर ब्राउन ज़्यादा भारी लगे, तो पिंक आज़माएँ। व्हाइट सबसे तीखी है और उसे नज़रअंदाज़ करना सबसे मुश्किल।"
        },
        {
          "name": "प्ले दबाएँ",
          "text": "पहला टैप आपके ब्राउज़र में ऑडियो इंजन बनाता है। धीमे फ़ोन पर इसे आधा सेकंड दें। उसके बाद आवाज़ बदलना फ़ौरन होता है।"
        },
        {
          "name": "अपना वॉल्यूम ढूँढें",
          "text": "इतना कम कि आपसे सामान्य आवाज़ में बात करने वाला कोई इंसान आपको फिर भी सुनाई दे। अगर उसके ऊपर सुनाई देने के लिए आपको आवाज़ ऊँची करनी पड़े, तो वॉल्यूम बहुत ज़्यादा है।"
        },
        {
          "name": "ज़रूरत हो तो स्लीप टाइमर लगाएँ",
          "text": "15, 30, 60 या 90 मिनट चुनें। आख़िर में आवाज़ धीरे-धीरे मद्धम होकर बंद हो जाती है, ताकि आप चौंकें नहीं। अगर इसे पूरे दिन चलाना है, तो टाइमर बंद ही रहने दें।"
        }
      ]
    },
    {
      "kind": "paragraphs",
      "heading": "ब्राउन नॉइज़ ADHD दिमाग़ों के लिए क्यों काम करता है",
      "paragraphs": [
        "ADHD दिमाग़ नई आवाज़ों की तरफ़ मुड़ जाते हैं। दरवाज़े का धड़ाम से बंद होना, फ़ोन की घरघराहट, पीछे बैठे दो लोगों का बातें शुरू कर देना। इनमें से हर एक आपके ध्यान का एक धागा उस काम से खींच लेती है जो आप कर रहे थे, और उसे वापस लाने में सचमुच समय और मेहनत लगती है।",
        "ब्राउन नॉइज़ आपसे फ़ोकस नहीं करवाता। यह उन चीज़ों को हटा देता है जो बार-बार आपका फ़ोकस खींच ले जाती हैं। एक ठहरी हुई, अंदाज़ा लगाने लायक आवाज़ उन बेतरतीब आवाज़ों को ढक देती है, जिससे आपका दिमाग़ हर कुछ सेकंड में चौंककर मुड़ना बंद कर देता है।",
        "यहाँ एक छोटी, पर दिलचस्प शोध की बात भी है। 2007 की एक स्टडी में [Söderlund, Sikström, and Smart](https://onlinelibrary.wiley.com/doi/10.1111/j.1469-7610.2007.01749.x) ने पाया कि मध्यम स्तर के व्हाइट नॉइज़ ने ध्यान की दिक्कतों वाले बच्चों के संज्ञानात्मक प्रदर्शन को बेहतर किया, जबकि न्यूरोटिपिकल बच्चों के प्रदर्शन को उसने थोड़ा नुक़सान पहुँचाया। इसके पीछे सुझाई गई प्रक्रिया है स्टोकेस्टिक रेज़ोनेंस, यानी यह विचार कि एक शोर भरे दिमाग़ को अपनी सही कार्य-सीमा में आने के लिए शायद थोड़े बाहरी शोर की ज़रूरत होती है।",
        "विज्ञान अभी शुरुआती दौर में है, लेकिन जिन्होंने इसे जिया है उनके अनुभव ऊँची आवाज़ में और एक जैसे हैं। [CHADD](https://chadd.org/about-adhd/overview/) और इस तरह की दूसरी संस्थाएँ बैकग्राउंड साउंड जैसे संवेदी औज़ारों को आज़माने लायक एक वाजिब चीज़ मानती हैं। अगर यह आपकी मदद करता है, तो इतना ही काफ़ी है।"
      ]
    },
    {
      "kind": "faq",
      "heading": "अक्सर पूछे जाने वाले सवाल",
      "faqs": [
        {
          "q": "ब्राउन नॉइज़ क्या है?",
          "a": "ब्राउन नॉइज़ एक गहरी, गड़गड़ाहट जैसी आवाज़ है जिसमें कम फ़्रीक्वेंसी वाली ऊर्जा ज़्यादा होती है। इसका नाम उसी बेतरतीब \"ब्राउनियन मोशन\" वाले गणित पर पड़ा है जो इसे बनाता है। यह किसी लगातार बहते झरने या छत पर पड़ती तेज़ बारिश जैसी सुनाई देती है। व्हाइट नॉइज़ के मुक़ाबले यह ज़्यादा गहरी और गर्म है, जो ज़्यादातर लोगों को लंबे सेशन के लिए कम चुभने वाली लगती है।"
        },
        {
          "q": "क्या यह एक एंबिएंट साउंड जनरेटर है?",
          "a": "हाँ। ब्राउन नॉइज़ सबसे लोकप्रिय सेटिंग है, पर यही प्लेयर पिंक और व्हाइट भी बनाता है। कुल तीन एंबिएंट आवाज़ें, और सब आपके ब्राउज़र में उसी वक़्त बनती हैं, बिना कोई ऑडियो फ़ाइल डाउनलोड किए। जो भी आवाज़ आपके दिमाग़ के लिए बैकग्राउंड में घुल जाए, वही चुनें।"
        },
        {
          "q": "ब्राउन नॉइज़, पिंक नॉइज़ और व्हाइट नॉइज़ में से मुझे कौन-सा चुनना चाहिए?",
          "a": "व्हाइट नॉइज़ सभी फ़्रीक्वेंसी पर बराबर होता है और टीवी की सरसराहट जैसा सुनाई देता है। पिंक नॉइज़ ऊँची फ़्रीक्वेंसी को थोड़ा कम कर देता है, इसलिए वह ज़्यादा नरम लगता है, जैसे लगातार होती बारिश। ब्राउन नॉइज़ उन्हें और भी कम कर देता है, इसलिए वह गहरा और टिकाने वाला लगता है। अगर व्हाइट नॉइज़ चुभे, तो पिंक आज़माएँ। अगर पिंक भी तीखा लगे, तो ब्राउन आज़माएँ। वही चुनें जिसे आप आराम से नज़रअंदाज़ कर सकें।"
        },
        {
          "q": "क्या ब्राउन नॉइज़ ADHD फ़ोकस के लिए अच्छा है?",
          "a": "कुछ ADHD वयस्क लगातार चलती बैकग्राउंड आवाज़ के साथ बेहतर फ़ोकस कर पाते हैं, और Söderlund और उनके साथियों की 2007 की एक स्टडी में पाया गया कि मध्यम स्तर के श्रवण शोर ने ध्यान की दिक्कतों वाले बच्चों के संज्ञानात्मक प्रदर्शन को सचमुच बेहतर किया। इसके पीछे की वजह शायद मास्किंग है। एक ठहरी हुई आवाज़ बेतरतीब आवाज़ों (बातचीत, ट्रैफ़िक, गुनगुनाता फ़्रिज) को ढक देती है, जिससे आपका दिमाग़ हर नई आवाज़ की तरफ़ मुड़ना बंद कर देता है।"
        },
        {
          "q": "क्या पूरे दिन ब्राउन नॉइज़ सुनना सुरक्षित है?",
          "a": "हाँ, वाजिब वॉल्यूम पर। सुनने की सेहत के वही नियम यहाँ भी लागू होते हैं जो संगीत पर होते हैं। वॉल्यूम इतना कम रखें कि उसी कमरे में सामान्य आवाज़ में बोलते किसी इंसान को आप आराम से सुन सकें। CDC 70 dB से ऊपर लंबे समय तक आवाज़ के संपर्क में रहने को सीमित करने की सलाह देता है। अगर किसी सेशन के बाद आपके कान थके हुए लगें या उनमें सीटी जैसी आवाज़ हो, तो वॉल्यूम बहुत ज़्यादा है।"
        },
        {
          "q": "ब्राउन नॉइज़ TikTok पर ट्रेंड क्यों कर रहा है?",
          "a": "TikTok पर ADHD वयस्कों ने पोस्ट करना शुरू किया कि ब्राउन नॉइज़ ने उनके अंदर लगातार चलती दिमाग़ी बड़बड़ाहट को शांत कर दिया, जिसे अक्सर यूँ बताया गया कि \"मेरे सिर का शोर ग़ायब हो गया।\" यही एक बात 2022 और 2023 में वायरल हो गई, और लोगों की एक पूरी लहर ने इसे आज़माया। विज्ञान अभी शुरुआती दौर में है, पर जिन्होंने इसे जिया है उनके अनुभव इतने मज़बूत हैं कि इसे ख़ुद आज़माकर देखना बनता है।"
        },
        {
          "q": "क्या यह ऑफ़लाइन काम करता है?",
          "a": "हाँ। आवाज़ आपके ब्राउज़र में Web Audio API की मदद से बनाई जाती है, किसी सर्वर से स्ट्रीम नहीं की जाती। पेज एक बार लोड हो जाए, उसके बाद इंटरनेट कनेक्शन की ज़रूरत नहीं। कुछ भी रिकॉर्ड नहीं होता, कुछ भी अपलोड नहीं होता, और प्लेयर में न कोई विज्ञापन है, न ट्रैकर।"
        }
      ]
    }
  ],
  "related": {
    "heading": "मिलते-जुलते टूल",
    "body": "ब्राउन नॉइज़ किसी फ़ोकस टाइमर के साथ बख़ूबी जमता है। 25 मिनट के तयशुदा स्प्रिंट के लिए [ADHD पोमोडोरो टाइमर](/tools/pomodoro) आज़माएँ, या अगर आपको घटता हुआ पाई-वेज चाहिए जो टाइम-ब्लाइंडनेस घड़ी का भी काम करे, तो [विज़ुअल टाइमर](/tools/visual-timer) देखें। [पूरी टूल लाइब्रेरी](/tools) देखें, या फ़ोकस, ब्रेन डंपिंग और अटकन से बाहर निकलने पर गाइड्स के लिए [Doubly लर्न लाइब्रेरी](/learn) पढ़ें।"
  },
  "cards": null,
  "openTool": null,
  "comingSoon": null,
  "cta": {
    "headline": "इसे ऐप में आज़माएँ",
    "body": "ब्राउन नॉइज़ आपको किसी काम में जमने में मदद करता है। Doubly iOS ऐप यह चुनने में मदद करता है कि काम कौन-सा हो। ब्रेन डंप, एक साफ़ अगला कदम, और असली लोगों के जवाबदेही चेक-इन।",
    "label": "इसे ऐप में आज़माएँ"
  },
  "jsonld": {
    "appName": "Doubly ब्राउन नॉइज़ जनरेटर",
    "appDescription": "पिंक और व्हाइट के साथ एक मुफ़्त ब्राउन नॉइज़ जनरेटर, जो सीधे ब्राउज़र में चलता है। न साइन-अप, स्लीप टाइमर शामिल, ऑफ़लाइन भी काम करता है।",
    "howToName": "ब्राउन नॉइज़ जनरेटर का इस्तेमाल कैसे करें",
    "collectionName": null,
    "collectionDescription": null
  }
}
